{
  "status": true,
  "timestamp": 1738589267081,
  "sessionId": "ed668532-2c73-4d8b-8cb9-1f45e718e88b",
  "data": {
    "context": {
      "status": "incomplete",
      "sessionId": "Cl0IARJZCk4KJGVkNjY4NTMyLTJjNzMtNGQ4Yi04Y2I5LTFmNDVlNzE4ZTg4YhACGiQ2M2YyYTlkYy0wODM5LTQzMWQtYjMyMC1hYTFjYzUyNDU2NTUQr73738wyGAESKHVzc19jMGI3NGFlNi02ZTRhLTQwNGItYmVjOC0wNGIxNzg0OWYyNTEiAlVT",
      "totalResults": 10
    },
    "itineraries": [
      {
        "id": "13542-2502041300--30598-0-12712-2502041550",
        "price": {
          "raw": 529.99,
          "formatted": "$530",
          "pricingOptionId": "r6DKYw3HEOQi"
        },
        "legs": [
          {
            "id": "13542-2502041300--30598-0-12712-2502041550",
            "origin": {
              "id": "LGW",
              "entityId": "95565051",
              "name": "London Gatwick",
              "displayCode": "LGW",
              "city": "London",
              "country": "United Kingdom",
              "isHighlighted": false
            },
            "destination": {
              "id": "JFK",
              "entityId": "95565058",
              "name": "New York John F. Kennedy",
              "displayCode": "JFK",
              "city": "New York",
              "country": "United States",
              "isHighlighted": false
            },
            "durationInMinutes": 470,
            "stopCount": 0,
            "isSmallestStops": false,
            "departure": "2025-02-04T13:00:00",
            "arrival": "2025-02-04T15:50:00",
            "timeDeltaInDays": 0,
            "carriers": {
              "marketing": [
                {
                  "id": -30598,
                  "alternateId": "I)",
                  "logoUrl": "https://logos.skyscnr.com/images/airlines/favicon/I%29.png",
                  "name": "Norse Atlantic Airways (UK)"
                }
              ],
              "operationType": "fully_operated"
            },
            "segments": [
              {
                "id": "13542-12712-2502041300-2502041550--30598",
                "origin": {
                  "flightPlaceId": "LGW",
                  "displayCode": "LGW",
                  "parent": {
                    "flightPlaceId": "LOND",
                    "displayCode": "LON",
                    "name": "London",
                    "type": "City"
                  },
                  "name": "London Gatwick",
                  "type": "Airport",
                  "country": "United Kingdom"
                },
                "destination": {
                  "flightPlaceId": "JFK",
                  "displayCode": "JFK",
                  "parent": {
                    "flightPlaceId": "NYCA",
                    "displayCode": "NYC",
                    "name": "New York",
                    "type": "City"
                  },
                  "name": "New York John F. Kennedy",
                  "type": "Airport",
                  "country": "United States"
                },
                "departure": "2025-02-04T13:00:00",
                "arrival": "2025-02-04T15:50:00",
                "durationInMinutes": 470,
                "flightNumber": "701",
                "marketingCarrier": {
                  "id": -30598,
                  "name": "Norse Atlantic Airways (UK)",
                  "alternateId": "I)",
                  "allianceId": 0,
                  "displayCode": ""
                },
                "operatingCarrier": {
                  "id": -30598,
                  "name": "Norse Atlantic Airways (UK)",
                  "alternateId": "I)",
                  "allianceId": 0,
                  "displayCode": ""
                }
              }
            ]
          }
        ],
        "isSelfTransfer": false,
        "isProtectedSelfTransfer": false,
        "farePolicy": {
          "isChangeAllowed": false,
          "isPartiallyChangeable": false,
          "isCancellationAllowed": false,
          "isPartiallyRefundable": false
        },
        "eco": { "ecoContenderDelta": 10.7372875 },
        "fareAttributes": {},
        "tags": ["shortest"],
        "isMashUp": false,
        "hasFlexibleOptions": false,
        "score": 0.999
      },
      {
        "id": "13554-2502041220--32171-0-12712-2502041551",
        "price": {
          "raw": 917.81,
          "formatted": "$918",
          "pricingOptionId": "H7z82-B210UJ"
        },
        "legs": [
          {
            "id": "13554-2502041220--32171-0-12712-2502041551",
            "origin": {
              "id": "LHR",
              "entityId": "95565050",
              "name": "London Heathrow",
              "displayCode": "LHR",
              "city": "London",
              "country": "United Kingdom",
              "isHighlighted": false
            },
            "destination": {
              "id": "JFK",
              "entityId": "95565058",
              "name": "New York John F. Kennedy",
              "displayCode": "JFK",
              "city": "New York",
              "country": "United States",
              "isHighlighted": false
            },
            "durationInMinutes": 511,
            "stopCount": 0,
            "isSmallestStops": false,
            "departure": "2025-02-04T12:20:00",
            "arrival": "2025-02-04T15:51:00",
            "timeDeltaInDays": 0,
            "carriers": {
              "marketing": [
                {
                  "id": -32171,
                  "alternateId": "B6",
                  "logoUrl": "https://logos.skyscnr.com/images/airlines/favicon/B6.png",
                  "name": "jetBlue"
                }
              ],
              "operationType": "fully_operated"
            },
            "segments": [
              {
                "id": "13554-12712-2502041220-2502041551--32171",
                "origin": {
                  "flightPlaceId": "LHR",
                  "displayCode": "LHR",
                  "parent": {
                    "flightPlaceId": "LOND",
                    "displayCode": "LON",
                    "name": "London",
                    "type": "City"
                  },
                  "name": "London Heathrow",
                  "type": "Airport",
                  "country": "United Kingdom"
                },
                "destination": {
                  "flightPlaceId": "JFK",
                  "displayCode": "JFK",
                  "parent": {
                    "flightPlaceId": "NYCA",
                    "displayCode": "NYC",
                    "name": "New York",
                    "type": "City"
                  },
                  "name": "New York John F. Kennedy",
                  "type": "Airport",
                  "country": "United States"
                },
                "departure": "2025-02-04T12:20:00",
                "arrival": "2025-02-04T15:51:00",
                "durationInMinutes": 511,
                "flightNumber": "20",
                "marketingCarrier": {
                  "id": -32171,
                  "name": "jetBlue",
                  "alternateId": "B6",
                  "allianceId": 0,
                  "displayCode": ""
                },
                "operatingCarrier": {
                  "id": -32171,
                  "name": "jetBlue",
                  "alternateId": "B6",
                  "allianceId": 0,
                  "displayCode": ""
                }
              }
            ]
          }
        ],
        "isSelfTransfer": false,
        "isProtectedSelfTransfer": false,
        "farePolicy": {
          "isChangeAllowed": false,
          "isPartiallyChangeable": false,
          "isCancellationAllowed": false,
          "isPartiallyRefundable": false
        },
        "fareAttributes": {},
        "isMashUp": false,
        "hasFlexibleOptions": false,
        "score": 0.642666
      },
      {
        "id": "13554-2502040950--32753-1-11442-2502041610",
        "price": {
          "raw": 497.91,
          "formatted": "$498",
          "pricingOptionId": "Pd-cBaMFxtRo"
        },
        "legs": [
          {
            "id": "13554-2502040950--32753-1-11442-2502041610",
            "origin": {
              "id": "LHR",
              "entityId": "95565050",
              "name": "London Heathrow",
              "displayCode": "LHR",
              "city": "London",
              "country": "United Kingdom",
              "isHighlighted": false
            },
            "destination": {
              "id": "EWR",
              "entityId": "95565059",
              "name": "New York Newark",
              "displayCode": "EWR",
              "city": "New York",
              "country": "United States",
              "isHighlighted": false
            },
            "durationInMinutes": 680,
            "stopCount": 1,
            "isSmallestStops": false,
            "departure": "2025-02-04T09:50:00",
            "arrival": "2025-02-04T16:10:00",
            "timeDeltaInDays": 0,
            "carriers": {
              "marketing": [
                {
                  "id": -32753,
                  "alternateId": "EI",
                  "logoUrl": "https://logos.skyscnr.com/images/airlines/favicon/EI.png",
                  "name": "Aer Lingus"
                }
              ],
              "operationType": "fully_operated"
            },
            "segments": [
              {
                "id": "13554-11154-2502040950-2502041115--32753",
                "origin": {
                  "flightPlaceId": "LHR",
                  "displayCode": "LHR",
                  "parent": {
                    "flightPlaceId": "LOND",
                    "displayCode": "LON",
                    "name": "London",
                    "type": "City"
                  },
                  "name": "London Heathrow",
                  "type": "Airport",
                  "country": "United Kingdom"
                },
                "destination": {
                  "flightPlaceId": "DUB",
                  "displayCode": "DUB",
                  "parent": {
                    "flightPlaceId": "DUBL",
                    "displayCode": "DUB",
                    "name": "Dublin",
                    "type": "City"
                  },
                  "name": "Dublin",
                  "type": "Airport",
                  "country": "Ireland"
                },
                "departure": "2025-02-04T09:50:00",
                "arrival": "2025-02-04T11:15:00",
                "durationInMinutes": 85,
                "flightNumber": "155",
                "marketingCarrier": {
                  "id": -32753,
                  "name": "Aer Lingus",
                  "alternateId": "EI",
                  "allianceId": 0,
                  "displayCode": ""
                },
                "operatingCarrier": {
                  "id": -32753,
                  "name": "Aer Lingus",
                  "alternateId": "EI",
                  "allianceId": 0,
                  "displayCode": ""
                }
              },
              {
                "id": "11154-11442-2502041310-2502041610--32753",
                "origin": {
                  "flightPlaceId": "DUB",
                  "displayCode": "DUB",
                  "parent": {
                    "flightPlaceId": "DUBL",
                    "displayCode": "DUB",
                    "name": "Dublin",
                    "type": "City"
                  },
                  "name": "Dublin",
                  "type": "Airport",
                  "country": "Ireland"
                },
                "destination": {
                  "flightPlaceId": "EWR",
                  "displayCode": "EWR",
                  "parent": {
                    "flightPlaceId": "NYCA",
                    "displayCode": "NYC",
                    "name": "New York",
                    "type": "City"
                  },
                  "name": "New York Newark",
                  "type": "Airport",
                  "country": "United States"
                },
                "departure": "2025-02-04T13:10:00",
                "arrival": "2025-02-04T16:10:00",
                "durationInMinutes": 480,
                "flightNumber": "101",
                "marketingCarrier": {
                  "id": -32753,
                  "name": "Aer Lingus",
                  "alternateId": "EI",
                  "allianceId": 0,
                  "displayCode": ""
                },
                "operatingCarrier": {
                  "id": -32753,
                  "name": "Aer Lingus",
                  "alternateId": "EI",
                  "allianceId": 0,
                  "displayCode": ""
                }
              }
            ]
          }
        ],
        "isSelfTransfer": false,
        "isProtectedSelfTransfer": false,
        "farePolicy": {
          "isChangeAllowed": false,
          "isPartiallyChangeable": false,
          "isCancellationAllowed": false,
          "isPartiallyRefundable": false
        },
        "fareAttributes": {},
        "tags": ["third_cheapest"],
        "isMashUp": false,
        "hasFlexibleOptions": false,
        "score": 0.581372
      },
      {
        "id": "13542-2502041300--30846-0-12712-2502041550",
        "price": {
          "raw": 746.98,
          "formatted": "$747",
          "pricingOptionId": "XbJ0LOJxO6v-"
        },
        "legs": [
          {
            "id": "13542-2502041300--30846-0-12712-2502041550",
            "origin": {
              "id": "LGW",
              "entityId": "95565051",
              "name": "London Gatwick",
              "displayCode": "LGW",
              "city": "London",
              "country": "United Kingdom",
              "isHighlighted": false
            },
            "destination": {
              "id": "JFK",
              "entityId": "95565058",
              "name": "New York John F. Kennedy",
              "displayCode": "JFK",
              "city": "New York",
              "country": "United States",
              "isHighlighted": false
            },
            "durationInMinutes": 470,
            "stopCount": 0,
            "isSmallestStops": false,
            "departure": "2025-02-04T13:00:00",
            "arrival": "2025-02-04T15:50:00",
            "timeDeltaInDays": 0,
            "carriers": {
              "marketing": [
                {
                  "id": -30846,
                  "alternateId": "~P",
                  "logoUrl": "https://logos.skyscnr.com/images/airlines/favicon/%7EP.png",
                  "name": "APG Distribution System"
                }
              ],
              "operating": [
                {
                  "id": -30598,
                  "alternateId": "I)",
                  "logoUrl": "https://logos.skyscnr.com/images/airlines/favicon/I%29.png",
                  "name": "Norse Atlantic Airways (UK)"
                }
              ],
              "operationType": "not_operated"
            },
            "segments": [
              {
                "id": "13542-12712-2502041300-2502041550--30846",
                "origin": {
                  "flightPlaceId": "LGW",
                  "displayCode": "LGW",
                  "parent": {
                    "flightPlaceId": "LOND",
                    "displayCode": "LON",
                    "name": "London",
                    "type": "City"
                  },
                  "name": "London Gatwick",
                  "type": "Airport",
                  "country": "United Kingdom"
                },
                "destination": {
                  "flightPlaceId": "JFK",
                  "displayCode": "JFK",
                  "parent": {
                    "flightPlaceId": "NYCA",
                    "displayCode": "NYC",
                    "name": "New York",
                    "type": "City"
                  },
                  "name": "New York John F. Kennedy",
                  "type": "Airport",
                  "country": "United States"
                },
                "departure": "2025-02-04T13:00:00",
                "arrival": "2025-02-04T15:50:00",
                "durationInMinutes": 470,
                "flightNumber": "5951",
                "marketingCarrier": {
                  "id": -30846,
                  "name": "APG Distribution System",
                  "alternateId": "~P",
                  "allianceId": 0,
                  "displayCode": ""
                },
                "operatingCarrier": {
                  "id": -30598,
                  "name": "Norse Atlantic Airways (UK)",
                  "alternateId": "I)",
                  "allianceId": 0,
                  "displayCode": ""
                }
              }
            ]
          }
        ],
        "isSelfTransfer": false,
        "isProtectedSelfTransfer": false,
        "farePolicy": {
          "isChangeAllowed": false,
          "isPartiallyChangeable": false,
          "isCancellationAllowed": false,
          "isPartiallyRefundable": false
        },
        "eco": { "ecoContenderDelta": 10.7372875 },
        "fareAttributes": {},
        "tags": ["second_shortest"],
        "isMashUp": false,
        "hasFlexibleOptions": false,
        "score": 0.496795
      },
      {
        "id": "13554-2502040725--32171-0-12712-2502041049",
        "price": {
          "raw": 917.81,
          "formatted": "$918",
          "pricingOptionId": "pAPBPzE1Jdpa"
        },
        "legs": [
          {
            "id": "13554-2502040725--32171-0-12712-2502041049",
            "origin": {
              "id": "LHR",
              "entityId": "95565050",
              "name": "London Heathrow",
              "displayCode": "LHR",
              "city": "London",
              "country": "United Kingdom",
              "isHighlighted": false
            },
            "destination": {
              "id": "JFK",
              "entityId": "95565058",
              "name": "New York John F. Kennedy",
              "displayCode": "JFK",
              "city": "New York",
              "country": "United States",
              "isHighlighted": false
            },
            "durationInMinutes": 504,
            "stopCount": 0,
            "isSmallestStops": false,
            "departure": "2025-02-04T07:25:00",
            "arrival": "2025-02-04T10:49:00",
            "timeDeltaInDays": 0,
            "carriers": {
              "marketing": [
                {
                  "id": -32171,
                  "alternateId": "B6",
                  "logoUrl": "https://logos.skyscnr.com/images/airlines/favicon/B6.png",
                  "name": "jetBlue"
                }
              ],
              "operationType": "fully_operated"
            },
            "segments": [
              {
                "id": "13554-12712-2502040725-2502041049--32171",
                "origin": {
                  "flightPlaceId": "LHR",
                  "displayCode": "LHR",
                  "parent": {
                    "flightPlaceId": "LOND",
                    "displayCode": "LON",
                    "name": "London",
                    "type": "City"
                  },
                  "name": "London Heathrow",
                  "type": "Airport",
                  "country": "United Kingdom"
                },
                "destination": {
                  "flightPlaceId": "JFK",
                  "displayCode": "JFK",
                  "parent": {
                    "flightPlaceId": "NYCA",
                    "displayCode": "NYC",
                    "name": "New York",
                    "type": "City"
                  },
                  "name": "New York John F. Kennedy",
                  "type": "Airport",
                  "country": "United States"
                },
                "departure": "2025-02-04T07:25:00",
                "arrival": "2025-02-04T10:49:00",
                "durationInMinutes": 504,
                "flightNumber": "2220",
                "marketingCarrier": {
                  "id": -32171,
                  "name": "jetBlue",
                  "alternateId": "B6",
                  "allianceId": 0,
                  "displayCode": ""
                },
                "operatingCarrier": {
                  "id": -32171,
                  "name": "jetBlue",
                  "alternateId": "B6",
                  "allianceId": 0,
                  "displayCode": ""
                }
              }
            ]
          }
        ],
        "isSelfTransfer": false,
        "isProtectedSelfTransfer": false,
        "farePolicy": {
          "isChangeAllowed": false,
          "isPartiallyChangeable": false,
          "isCancellationAllowed": false,
          "isPartiallyRefundable": false
        },
        "fareAttributes": {},
        "isMashUp": false,
        "hasFlexibleOptions": false,
        "score": 0.472115
      },
      {
        "id": "13554-2502041340--31781-1-11442-2502042210",
        "price": {
          "raw": 481.97,
          "formatted": "$482",
          "pricingOptionId": "iUR6et4-j_fl"
        },
        "legs": [
          {
            "id": "13554-2502041340--31781-1-11442-2502042210",
            "origin": {
              "id": "LHR",
              "entityId": "95565050",
              "name": "London Heathrow",
              "displayCode": "LHR",
              "city": "London",
              "country": "United Kingdom",
              "isHighlighted": false
            },
            "destination": {
              "id": "EWR",
              "entityId": "95565059",
              "name": "New York Newark",
              "displayCode": "EWR",
              "city": "New York",
              "country": "United States",
              "isHighlighted": false
            },
            "durationInMinutes": 810,
            "stopCount": 1,
            "isSmallestStops": false,
            "departure": "2025-02-04T13:40:00",
            "arrival": "2025-02-04T22:10:00",
            "timeDeltaInDays": 0,
            "carriers": {
              "marketing": [
                {
                  "id": -31781,
                  "alternateId": "TP",
                  "logoUrl": "https://logos.skyscnr.com/images/airlines/favicon/TP.png",
                  "name": "TAP Air Portugal"
                }
              ],
              "operationType": "fully_operated"
            },
            "segments": [
              {
                "id": "13554-13577-2502041340-2502041625--31781",
                "origin": {
                  "flightPlaceId": "LHR",
                  "displayCode": "LHR",
                  "parent": {
                    "flightPlaceId": "LOND",
                    "displayCode": "LON",
                    "name": "London",
                    "type": "City"
                  },
                  "name": "London Heathrow",
                  "type": "Airport",
                  "country": "United Kingdom"
                },
                "destination": {
                  "flightPlaceId": "LIS",
                  "displayCode": "LIS",
                  "parent": {
                    "flightPlaceId": "LISB",
                    "displayCode": "LIS",
                    "name": "Lisbon",
                    "type": "City"
                  },
                  "name": "Lisbon",
                  "type": "Airport",
                  "country": "Portugal"
                },
                "departure": "2025-02-04T13:40:00",
                "arrival": "2025-02-04T16:25:00",
                "durationInMinutes": 165,
                "flightNumber": "1359",
                "marketingCarrier": {
                  "id": -31781,
                  "name": "TAP Air Portugal",
                  "alternateId": "TP",
                  "allianceId": 0,
                  "displayCode": ""
                },
                "operatingCarrier": {
                  "id": -31781,
                  "name": "TAP Air Portugal",
                  "alternateId": "TP",
                  "allianceId": 0,
                  "displayCode": ""
                }
              },
              {
                "id": "13577-11442-2502041845-2502042210--31781",
                "origin": {
                  "flightPlaceId": "LIS",
                  "displayCode": "LIS",
                  "parent": {
                    "flightPlaceId": "LISB",
                    "displayCode": "LIS",
                    "name": "Lisbon",
                    "type": "City"
                  },
                  "name": "Lisbon",
                  "type": "Airport",
                  "country": "Portugal"
                },
                "destination": {
                  "flightPlaceId": "EWR",
                  "displayCode": "EWR",
                  "parent": {
                    "flightPlaceId": "NYCA",
                    "displayCode": "NYC",
                    "name": "New York",
                    "type": "City"
                  },
                  "name": "New York Newark",
                  "type": "Airport",
                  "country": "United States"
                },
                "departure": "2025-02-04T18:45:00",
                "arrival": "2025-02-04T22:10:00",
                "durationInMinutes": 505,
                "flightNumber": "203",
                "marketingCarrier": {
                  "id": -31781,
                  "name": "TAP Air Portugal",
                  "alternateId": "TP",
                  "allianceId": 0,
                  "displayCode": ""
                },
                "operatingCarrier": {
                  "id": -31781,
                  "name": "TAP Air Portugal",
                  "alternateId": "TP",
                  "allianceId": 0,
                  "displayCode": ""
                }
              }
            ]
          }
        ],
        "isSelfTransfer": false,
        "isProtectedSelfTransfer": false,
        "farePolicy": {
          "isChangeAllowed": false,
          "isPartiallyChangeable": false,
          "isCancellationAllowed": false,
          "isPartiallyRefundable": false
        },
        "fareAttributes": {},
        "tags": ["second_cheapest"],
        "isMashUp": false,
        "hasFlexibleOptions": false,
        "score": 0.438939
      },
      {
        "id": "13542-2502041040--31781-1-11442-2502042210",
        "price": {
          "raw": 477.97,
          "formatted": "$478",
          "pricingOptionId": "jYi1DbS9NYOF"
        },
        "legs": [
          {
            "id": "13542-2502041040--31781-1-11442-2502042210",
            "origin": {
              "id": "LGW",
              "entityId": "95565051",
              "name": "London Gatwick",
              "displayCode": "LGW",
              "city": "London",
              "country": "United Kingdom",
              "isHighlighted": false
            },
            "destination": {
              "id": "EWR",
              "entityId": "95565059",
              "name": "New York Newark",
              "displayCode": "EWR",
              "city": "New York",
              "country": "United States",
              "isHighlighted": false
            },
            "durationInMinutes": 990,
            "stopCount": 1,
            "isSmallestStops": false,
            "departure": "2025-02-04T10:40:00",
            "arrival": "2025-02-04T22:10:00",
            "timeDeltaInDays": 0,
            "carriers": {
              "marketing": [
                {
                  "id": -31781,
                  "alternateId": "TP",
                  "logoUrl": "https://logos.skyscnr.com/images/airlines/favicon/TP.png",
                  "name": "TAP Air Portugal"
                }
              ],
              "operating": [
                {
                  "id": -31953,
                  "alternateId": "NI",
                  "logoUrl": "https://logos.skyscnr.com/images/airlines/favicon/NI.png",
                  "name": "Portugalia Airlines"
                }
              ],
              "operationType": "partially_operated"
            },
            "segments": [
              {
                "id": "13542-13577-2502041040-2502041320--31781",
                "origin": {
                  "flightPlaceId": "LGW",
                  "displayCode": "LGW",
                  "parent": {
                    "flightPlaceId": "LOND",
                    "displayCode": "LON",
                    "name": "London",
                    "type": "City"
                  },
                  "name": "London Gatwick",
                  "type": "Airport",
                  "country": "United Kingdom"
                },
                "destination": {
                  "flightPlaceId": "LIS",
                  "displayCode": "LIS",
                  "parent": {
                    "flightPlaceId": "LISB",
                    "displayCode": "LIS",
                    "name": "Lisbon",
                    "type": "City"
                  },
                  "name": "Lisbon",
                  "type": "Airport",
                  "country": "Portugal"
                },
                "departure": "2025-02-04T10:40:00",
                "arrival": "2025-02-04T13:20:00",
                "durationInMinutes": 160,
                "flightNumber": "1335",
                "marketingCarrier": {
                  "id": -31781,
                  "name": "TAP Air Portugal",
                  "alternateId": "TP",
                  "allianceId": 0,
                  "displayCode": ""
                },
                "operatingCarrier": {
                  "id": -31953,
                  "name": "Portugalia Airlines",
                  "alternateId": "NI",
                  "allianceId": 0,
                  "displayCode": ""
                }
              },
              {
                "id": "13577-11442-2502041845-2502042210--31781",
                "origin": {
                  "flightPlaceId": "LIS",
                  "displayCode": "LIS",
                  "parent": {
                    "flightPlaceId": "LISB",
                    "displayCode": "LIS",
                    "name": "Lisbon",
                    "type": "City"
                  },
                  "name": "Lisbon",
                  "type": "Airport",
                  "country": "Portugal"
                },
                "destination": {
                  "flightPlaceId": "EWR",
                  "displayCode": "EWR",
                  "parent": {
                    "flightPlaceId": "NYCA",
                    "displayCode": "NYC",
                    "name": "New York",
                    "type": "City"
                  },
                  "name": "New York Newark",
                  "type": "Airport",
                  "country": "United States"
                },
                "departure": "2025-02-04T18:45:00",
                "arrival": "2025-02-04T22:10:00",
                "durationInMinutes": 505,
                "flightNumber": "203",
                "marketingCarrier": {
                  "id": -31781,
                  "name": "TAP Air Portugal",
                  "alternateId": "TP",
                  "allianceId": 0,
                  "displayCode": ""
                },
                "operatingCarrier": {
                  "id": -31781,
                  "name": "TAP Air Portugal",
                  "alternateId": "TP",
                  "allianceId": 0,
                  "displayCode": ""
                }
              }
            ]
          }
        ],
        "isSelfTransfer": false,
        "isProtectedSelfTransfer": false,
        "farePolicy": {
          "isChangeAllowed": false,
          "isPartiallyChangeable": false,
          "isCancellationAllowed": false,
          "isPartiallyRefundable": false
        },
        "fareAttributes": {},
        "tags": ["cheapest"],
        "isMashUp": false,
        "hasFlexibleOptions": false,
        "score": 0.430347
      },
      {
        "id": "13554-2502040600--31781-1-11442-2502041530",
        "price": {
          "raw": 510.9,
          "formatted": "$511",
          "pricingOptionId": "-yMdJWSG2-UK"
        },
        "legs": [
          {
            "id": "13554-2502040600--31781-1-11442-2502041530",
            "origin": {
              "id": "LHR",
              "entityId": "95565050",
              "name": "London Heathrow",
              "displayCode": "LHR",
              "city": "London",
              "country": "United Kingdom",
              "isHighlighted": false
            },
            "destination": {
              "id": "EWR",
              "entityId": "95565059",
              "name": "New York Newark",
              "displayCode": "EWR",
              "city": "New York",
              "country": "United States",
              "isHighlighted": false
            },
            "durationInMinutes": 870,
            "stopCount": 1,
            "isSmallestStops": false,
            "departure": "2025-02-04T06:00:00",
            "arrival": "2025-02-04T15:30:00",
            "timeDeltaInDays": 0,
            "carriers": {
              "marketing": [
                {
                  "id": -31781,
                  "alternateId": "TP",
                  "logoUrl": "https://logos.skyscnr.com/images/airlines/favicon/TP.png",
                  "name": "TAP Air Portugal"
                }
              ],
              "operationType": "fully_operated"
            },
            "segments": [
              {
                "id": "13554-13577-2502040600-2502040840--31781",
                "origin": {
                  "flightPlaceId": "LHR",
                  "displayCode": "LHR",
                  "parent": {
                    "flightPlaceId": "LOND",
                    "displayCode": "LON",
                    "name": "London",
                    "type": "City"
                  },
                  "name": "London Heathrow",
                  "type": "Airport",
                  "country": "United Kingdom"
                },
                "destination": {
                  "flightPlaceId": "LIS",
                  "displayCode": "LIS",
                  "parent": {
                    "flightPlaceId": "LISB",
                    "displayCode": "LIS",
                    "name": "Lisbon",
                    "type": "City"
                  },
                  "name": "Lisbon",
                  "type": "Airport",
                  "country": "Portugal"
                },
                "departure": "2025-02-04T06:00:00",
                "arrival": "2025-02-04T08:40:00",
                "durationInMinutes": 160,
                "flightNumber": "1363",
                "marketingCarrier": {
                  "id": -31781,
                  "name": "TAP Air Portugal",
                  "alternateId": "TP",
                  "allianceId": 0,
                  "displayCode": ""
                },
                "operatingCarrier": {
                  "id": -31781,
                  "name": "TAP Air Portugal",
                  "alternateId": "TP",
                  "allianceId": 0,
                  "displayCode": ""
                }
              },
              {
                "id": "13577-11442-2502041205-2502041530--31781",
                "origin": {
                  "flightPlaceId": "LIS",
                  "displayCode": "LIS",
                  "parent": {
                    "flightPlaceId": "LISB",
                    "displayCode": "LIS",
                    "name": "Lisbon",
                    "type": "City"
                  },
                  "name": "Lisbon",
                  "type": "Airport",
                  "country": "Portugal"
                },
                "destination": {
                  "flightPlaceId": "EWR",
                  "displayCode": "EWR",
                  "parent": {
                    "flightPlaceId": "NYCA",
                    "displayCode": "NYC",
                    "name": "New York",
                    "type": "City"
                  },
                  "name": "New York Newark",
                  "type": "Airport",
                  "country": "United States"
                },
                "departure": "2025-02-04T12:05:00",
                "arrival": "2025-02-04T15:30:00",
                "durationInMinutes": 505,
                "flightNumber": "201",
                "marketingCarrier": {
                  "id": -31781,
                  "name": "TAP Air Portugal",
                  "alternateId": "TP",
                  "allianceId": 0,
                  "displayCode": ""
                },
                "operatingCarrier": {
                  "id": -31781,
                  "name": "TAP Air Portugal",
                  "alternateId": "TP",
                  "allianceId": 0,
                  "displayCode": ""
                }
              }
            ]
          }
        ],
        "isSelfTransfer": false,
        "isProtectedSelfTransfer": false,
        "farePolicy": {
          "isChangeAllowed": false,
          "isPartiallyChangeable": false,
          "isCancellationAllowed": false,
          "isPartiallyRefundable": false
        },
        "fareAttributes": {},
        "isMashUp": false,
        "hasFlexibleOptions": false,
        "score": 0.429415
      },
      {
        "id": "13554-2502040935--32222-0-12712-2502041240",
        "price": {
          "raw": 1012,
          "formatted": "$1,012",
          "pricingOptionId": "7RwVX76C6uV3"
        },
        "legs": [
          {
            "id": "13554-2502040935--32222-0-12712-2502041240",
            "origin": {
              "id": "LHR",
              "entityId": "95565050",
              "name": "London Heathrow",
              "displayCode": "LHR",
              "city": "London",
              "country": "United Kingdom",
              "isHighlighted": false
            },
            "destination": {
              "id": "JFK",
              "entityId": "95565058",
              "name": "New York John F. Kennedy",
              "displayCode": "JFK",
              "city": "New York",
              "country": "United States",
              "isHighlighted": false
            },
            "durationInMinutes": 485,
            "stopCount": 0,
            "isSmallestStops": false,
            "departure": "2025-02-04T09:35:00",
            "arrival": "2025-02-04T12:40:00",
            "timeDeltaInDays": 0,
            "carriers": {
              "marketing": [
                {
                  "id": -32222,
                  "alternateId": "IB",
                  "logoUrl": "https://logos.skyscnr.com/images/airlines/favicon/IB.png",
                  "name": "Iberia"
                }
              ],
              "operating": [
                {
                  "id": -32480,
                  "alternateId": "BA",
                  "logoUrl": "https://logos.skyscnr.com/images/airlines/favicon/BA.png",
                  "name": "British Airways"
                }
              ],
              "operationType": "not_operated"
            },
            "segments": [
              {
                "id": "13554-12712-2502040935-2502041240--32222",
                "origin": {
                  "flightPlaceId": "LHR",
                  "displayCode": "LHR",
                  "parent": {
                    "flightPlaceId": "LOND",
                    "displayCode": "LON",
                    "name": "London",
                    "type": "City"
                  },
                  "name": "London Heathrow",
                  "type": "Airport",
                  "country": "United Kingdom"
                },
                "destination": {
                  "flightPlaceId": "JFK",
                  "displayCode": "JFK",
                  "parent": {
                    "flightPlaceId": "NYCA",
                    "displayCode": "NYC",
                    "name": "New York",
                    "type": "City"
                  },
                  "name": "New York John F. Kennedy",
                  "type": "Airport",
                  "country": "United States"
                },
                "departure": "2025-02-04T09:35:00",
                "arrival": "2025-02-04T12:40:00",
                "durationInMinutes": 485,
                "flightNumber": "3561",
                "marketingCarrier": {
                  "id": -32222,
                  "name": "Iberia",
                  "alternateId": "IB",
                  "allianceId": 0,
                  "displayCode": ""
                },
                "operatingCarrier": {
                  "id": -32480,
                  "name": "British Airways",
                  "alternateId": "BA",
                  "allianceId": 0,
                  "displayCode": ""
                }
              }
            ]
          }
        ],
        "isSelfTransfer": false,
        "isProtectedSelfTransfer": false,
        "farePolicy": {
          "isChangeAllowed": false,
          "isPartiallyChangeable": false,
          "isCancellationAllowed": false,
          "isPartiallyRefundable": false
        },
        "fareAttributes": {},
        "tags": ["third_shortest"],
        "isMashUp": false,
        "hasFlexibleOptions": false,
        "score": 0.42276
      },
      {
        "id": "13554-2502041210--32753-1-12712-2502041929",
        "price": {
          "raw": 497.91,
          "formatted": "$498",
          "pricingOptionId": "uItugEhr1jBF"
        },
        "legs": [
          {
            "id": "13554-2502041210--32753-1-12712-2502041929",
            "origin": {
              "id": "LHR",
              "entityId": "95565050",
              "name": "London Heathrow",
              "displayCode": "LHR",
              "city": "London",
              "country": "United Kingdom",
              "isHighlighted": false
            },
            "destination": {
              "id": "JFK",
              "entityId": "95565058",
              "name": "New York John F. Kennedy",
              "displayCode": "JFK",
              "city": "New York",
              "country": "United States",
              "isHighlighted": false
            },
            "durationInMinutes": 739,
            "stopCount": 1,
            "isSmallestStops": false,
            "departure": "2025-02-04T12:10:00",
            "arrival": "2025-02-04T19:29:00",
            "timeDeltaInDays": 0,
            "carriers": {
              "marketing": [
                {
                  "id": -32753,
                  "alternateId": "EI",
                  "logoUrl": "https://logos.skyscnr.com/images/airlines/favicon/EI.png",
                  "name": "Aer Lingus"
                }
              ],
              "operationType": "fully_operated"
            },
            "segments": [
              {
                "id": "13554-11154-2502041210-2502041335--32753",
                "origin": {
                  "flightPlaceId": "LHR",
                  "displayCode": "LHR",
                  "parent": {
                    "flightPlaceId": "LOND",
                    "displayCode": "LON",
                    "name": "London",
                    "type": "City"
                  },
                  "name": "London Heathrow",
                  "type": "Airport",
                  "country": "United Kingdom"
                },
                "destination": {
                  "flightPlaceId": "DUB",
                  "displayCode": "DUB",
                  "parent": {
                    "flightPlaceId": "DUBL",
                    "displayCode": "DUB",
                    "name": "Dublin",
                    "type": "City"
                  },
                  "name": "Dublin",
                  "type": "Airport",
                  "country": "Ireland"
                },
                "departure": "2025-02-04T12:10:00",
                "arrival": "2025-02-04T13:35:00",
                "durationInMinutes": 85,
                "flightNumber": "159",
                "marketingCarrier": {
                  "id": -32753,
                  "name": "Aer Lingus",
                  "alternateId": "EI",
                  "allianceId": 0,
                  "displayCode": ""
                },
                "operatingCarrier": {
                  "id": -32753,
                  "name": "Aer Lingus",
                  "alternateId": "EI",
                  "allianceId": 0,
                  "displayCode": ""
                }
              },
              {
                "id": "11154-12712-2502041640-2502041929--32753",
                "origin": {
                  "flightPlaceId": "DUB",
                  "displayCode": "DUB",
                  "parent": {
                    "flightPlaceId": "DUBL",
                    "displayCode": "DUB",
                    "name": "Dublin",
                    "type": "City"
                  },
                  "name": "Dublin",
                  "type": "Airport",
                  "country": "Ireland"
                },
                "destination": {
                  "flightPlaceId": "JFK",
                  "displayCode": "JFK",
                  "parent": {
                    "flightPlaceId": "NYCA",
                    "displayCode": "NYC",
                    "name": "New York",
                    "type": "City"
                  },
                  "name": "New York John F. Kennedy",
                  "type": "Airport",
                  "country": "United States"
                },
                "departure": "2025-02-04T16:40:00",
                "arrival": "2025-02-04T19:29:00",
                "durationInMinutes": 469,
                "flightNumber": "107",
                "marketingCarrier": {
                  "id": -32753,
                  "name": "Aer Lingus",
                  "alternateId": "EI",
                  "allianceId": 0,
                  "displayCode": ""
                },
                "operatingCarrier": {
                  "id": -32753,
                  "name": "Aer Lingus",
                  "alternateId": "EI",
                  "allianceId": 0,
                  "displayCode": ""
                }
              }
            ]
          }
        ],
        "isSelfTransfer": false,
        "isProtectedSelfTransfer": false,
        "farePolicy": {
          "isChangeAllowed": false,
          "isPartiallyChangeable": false,
          "isCancellationAllowed": false,
          "isPartiallyRefundable": false
        },
        "fareAttributes": {},
        "isMashUp": false,
        "hasFlexibleOptions": false,
        "score": 0.421989
      }
    ],
    "messages": [],
    "filterStats": {
      "duration": {
        "min": 470,
        "max": 990,
        "multiCityMin": 470,
        "multiCityMax": 990
      },
      "airports": [
        {
          "city": "London",
          "airports": [
            { "id": "LGW", "entityId": "95565051", "name": "London Gatwick" },
            { "id": "LHR", "entityId": "95565050", "name": "London Heathrow" }
          ]
        },
        {
          "city": "New York",
          "airports": [
            {
              "id": "JFK",
              "entityId": "95565058",
              "name": "New York John F. Kennedy"
            },
            { "id": "EWR", "entityId": "95565059", "name": "New York Newark" }
          ]
        }
      ],
      "carriers": [
        {
          "id": -32753,
          "alternateId": "EI",
          "logoUrl": "https://logos.skyscnr.com/images/airlines/favicon/EI.png",
          "name": "Aer Lingus"
        },
        {
          "id": -30846,
          "alternateId": "~P",
          "logoUrl": "https://logos.skyscnr.com/images/airlines/favicon/%7EP.png",
          "name": "APG Distribution System"
        },
        {
          "id": -32222,
          "alternateId": "IB",
          "logoUrl": "https://logos.skyscnr.com/images/airlines/favicon/IB.png",
          "name": "Iberia"
        },
        {
          "id": -32171,
          "alternateId": "B6",
          "logoUrl": "https://logos.skyscnr.com/images/airlines/favicon/B6.png",
          "name": "jetBlue"
        },
        {
          "id": -30598,
          "alternateId": "I)",
          "logoUrl": "https://logos.skyscnr.com/images/airlines/favicon/I%29.png",
          "name": "Norse Atlantic Airways (UK)"
        },
        {
          "id": -31781,
          "alternateId": "TP",
          "logoUrl": "https://logos.skyscnr.com/images/airlines/favicon/TP.png",
          "name": "TAP Air Portugal"
        }
      ],
      "stopPrices": {
        "direct": { "isPresent": true, "formattedPrice": "$530" },
        "one": { "isPresent": true, "formattedPrice": "$478" },
        "twoOrMore": { "isPresent": false }
      }
    },
    "flightsSessionId": "ed668532-2c73-4d8b-8cb9-1f45e718e88b",
    "destinationImageUrl": "https://content.skyscnr.com/m/3719e8f4a5daf43d/original/Flights-Placeholder.jpg"
  }
}
